CLASSIFIERS.txt
LICENSE
MANIFEST.in
README.md
requirements.pip
setup.py
django_stalefields.egg-info/PKG-INFO
django_stalefields.egg-info/SOURCES.txt
django_stalefields.egg-info/dependency_links.txt
django_stalefields.egg-info/top_level.txt
example_app/__init__.py
example_app/manage.py
example_app/settings.py
example_app/urls.py
example_app/testing_app/__init__.py
example_app/testing_app/models.py
example_app/testing_app/tests.py
stalefields/__init__.py
stalefields/models.py
stalefields/stalefields.py