Metadata-Version: 1.0
Name: django-stalefields
Version: 0.8.5
Summary: Tracking stale fields on a Django model instance
Home-page: http://github.com/zapier/django-stalefields
Author: Simon de Haan & Corey Oordt & Bryan Helmig
Author-email: bryan@zapier.com
License: BSD
Platform: UNKNOWN
Classifier: Development Status :: 5 - Production/Stable
Classifier: Intended Audience :: Developers
Classifier: License :: OSI Approved :: BSD License
Classifier: Operating System :: OS Independent
Classifier: Programming Language :: Python
Classifier: Framework :: Django
Classifier: Topic :: Software Development :: Libraries :: Python Modules
